slurm_cancel/__init__.py
slurm_cancel/utils.py
slurm_cancel-0.1.6.dist-info/METADATA
slurm_cancel-0.1.6.dist-info/WHEEL
slurm_cancel-0.1.6.dist-info/top_level.txt
slurm_cancel-0.1.6.dist-info/RECORD
