Metadata-Version: 2.1
Name: slurm-cancel
Version: 0.1.6
Summary: Cancel Current Job in Slurm
Author: Muhammad Anas Raza
License: MIT
Platform: UNKNOWN
